LICENSE
README.md
setup.cfg
setup.py
resype/__init__.py
resype/cb_model.py
resype/collab_filtering.py
resype/content_based.py
resype/evaluate.py
resype/preprocessing.py
resype.egg-info/PKG-INFO
resype.egg-info/SOURCES.txt
resype.egg-info/dependency_links.txt
resype.egg-info/requires.txt
resype.egg-info/top_level.txt