Metadata-Version: 2.1
Name: resype
Version: 0.1
Summary: recommender system using machine learning
Home-page: https://github.com/phdinds-aim/resype
Author: Prince Javier
Author-email: othepjavier@gmail.com
License: MIT
Download-URL: https://github.com/phdinds-aim/resype/archive/refs/tags/v_01.tar.gz
Keywords: machine learning,recommender system
Platform: UNKNOWN
Classifier: Development Status :: 3 - Alpha
Classifier: Intended Audience :: Developers
Classifier: Topic :: Software Development :: Build Tools
Classifier: License :: OSI Approved :: MIT License
Classifier: Programming Language :: Python :: 3
Classifier: Programming Language :: Python :: 3.4
Classifier: Programming Language :: Python :: 3.5
Classifier: Programming Language :: Python :: 3.6
Classifier: Programming Language :: Python :: 3.7
Classifier: Programming Language :: Python :: 3.8
Classifier: Programming Language :: Python :: 3.9
Classifier: Programming Language :: Python :: 3.10
License-File: LICENSE
